pywebuikit/__init__.py
pywebuikit/test.py
pywebuikit/_dpd_threadckeck/__init__.py
pywebuikit/_real_overload/__init__.py
pywebuikit/fserver/__init__.py
pywebuikit/jsapi/__init__.py
pywebuikit/jsbridge/__init__.py
pywebuikit/jscodes/__init__.py
pywebuikit/public_objects/__init__.py
pywebuikit/render/__init__.py
pywebuikit/render/render_items.py
pywebuikit/webwindow/__init__.py
pywebuikit-0.dist-info/LICENSE
pywebuikit-0.dist-info/METADATA
pywebuikit-0.dist-info/WHEEL
pywebuikit-0.dist-info/top_level.txt
pywebuikit-0.dist-info/RECORD
